TronGisPy/AeroTriangulation.py
TronGisPy/Algorithm.py
TronGisPy/CRS.py
TronGisPy/DEMProcessor.py
TronGisPy/GisIO.py
TronGisPy/Interpolation.py
TronGisPy/Normalizer.py
TronGisPy/Raster.py
TronGisPy/ShapeGrid.py
TronGisPy/SplittedImage.py
TronGisPy/TypeCast.py
TronGisPy/__init__.py
TronGisPy/io.py
TronGisPy/data/aereo_tif/131129d_29_0263_refined.tif
TronGisPy/data/aereo_tif_clipper/131129d_29_0263_clipper.dbf
TronGisPy/data/aereo_tif_clipper/131129d_29_0263_clipper.prj
TronGisPy/data/aereo_tif_clipper/131129d_29_0263_clipper.shp
TronGisPy/data/aereo_tif_clipper/131129d_29_0263_clipper.shx
TronGisPy/data/aero_triangulation/P_XYZs.npy
TronGisPy/data/clip_shp_by_shp/line_to_be_clipped.cpg
TronGisPy/data/clip_shp_by_shp/line_to_be_clipped.dbf
TronGisPy/data/clip_shp_by_shp/line_to_be_clipped.shp
TronGisPy/data/clip_shp_by_shp/line_to_be_clipped.shx
TronGisPy/data/clip_shp_by_shp/multiline_to_be_clipped.cpg
TronGisPy/data/clip_shp_by_shp/multiline_to_be_clipped.dbf
TronGisPy/data/clip_shp_by_shp/multiline_to_be_clipped.shp
TronGisPy/data/clip_shp_by_shp/multiline_to_be_clipped.shx
TronGisPy/data/clip_shp_by_shp/point_to_be_clipped.cpg
TronGisPy/data/clip_shp_by_shp/point_to_be_clipped.dbf
TronGisPy/data/clip_shp_by_shp/point_to_be_clipped.shp
TronGisPy/data/clip_shp_by_shp/point_to_be_clipped.shx
TronGisPy/data/clip_shp_by_shp/poly_to_be_clipped.cpg
TronGisPy/data/clip_shp_by_shp/poly_to_be_clipped.dbf
TronGisPy/data/clip_shp_by_shp/poly_to_be_clipped.shp
TronGisPy/data/clip_shp_by_shp/poly_to_be_clipped.shx
TronGisPy/data/clip_shp_by_shp/shp_clipper.cpg
TronGisPy/data/clip_shp_by_shp/shp_clipper.dbf
TronGisPy/data/clip_shp_by_shp/shp_clipper.shp
TronGisPy/data/clip_shp_by_shp/shp_clipper.shx
TronGisPy/data/dem_tif/crop_dem.tif
TronGisPy/data/flipped_gt/flipped_gt.tif
TronGisPy/data/interpolation/X_forinterpolation.tif
TronGisPy/data/interpolation/climate_points.dbf
TronGisPy/data/interpolation/climate_points.mshp
TronGisPy/data/interpolation/climate_points.prj
TronGisPy-1.4.8.dist-info/LICENSE.txt
TronGisPy-1.4.8.dist-info/METADATA
TronGisPy-1.4.8.dist-info/WHEEL
TronGisPy-1.4.8.dist-info/top_level.txt
TronGisPy-1.4.8.dist-info/RECORD
